deploy/__init__.py
deploy/git_manager.py
deploy/model_company_updater.py
deploy/readme_updater.py
deploy/s3_manager.py
deploy/version_manager.py
looqbox_components/__init__.py
looqbox_components/src/__init__.py
looqbox_components/src/main/__init__.py
looqbox_components/src/main/model/__init__.py
looqbox_components/src/main/model/card.py
looqbox_components/src/main/model/colors.py
looqbox_components/src/main/model/combo_question_link.py
looqbox_components/src/main/model/container.py
looqbox_components/src/main/model/plotly_figure.py
looqbox_components/src/main/model/progress_bar.py
looqbox_components/src/main/model/simple_card.py
looqbox_components/src/main/model/tag.py
looqbox_components/src/main/model/toplist.py
looqbox_components/src/main/resources/__init__.py
looqbox_components/src/main/resources/combo_question_link.html
looqbox_components/src/main/utils/__init__.py
looqbox_components/src/main/utils/parent_parameters.py
looqbox_components/src/main/utils/texts.py
looqbox_components/src/tests/__init__.py
looqbox_components/src/tests/test_looqbox_components.py
looqbox_components/src/tests/test_simple_card.py
looqbox_components-6.2.5.dist-info/METADATA
looqbox_components-6.2.5.dist-info/WHEEL
looqbox_components-6.2.5.dist-info/top_level.txt
looqbox_components-6.2.5.dist-info/RECORD
